<!-- hkaSkeleton @ 0xacaf600 -->

<hkobject class="hkaSkeleton">
	<hkparam name="name">ponytail00</hkparam>
	<hkparam name="parentIndices" numelements="4">
		-1 0 1 2
	</hkparam>
	<hkparam name="bones" numelements="4">
		0xacaf720 0xacaf740 0xacaf760 0xacaf780
	</hkparam>
	<hkparam name="referencePose" numelements="4">
		(-0.000352 0.087964 0.124868)(-0.435161 -0.557347 0.435160 0.557347)(1.000000 1.000000 1.000000)
		(0.035944 0.000000 -0.000000)(-0.000000 -0.000000 -0.575464 -0.817827)(1.000001 1.000000 1.000000)
		(0.079904 0.000000 0.000000)(0.000000 -0.000000 -0.328762 -0.944413)(1.000036 1.000000 1.000000)
		(0.092878 0.000000 -0.000000)(-0.000000 0.000000 0.147676 -0.989036)(0.999964 1.000000 1.000000)
	</hkparam>
	<hkparam name="floatSlots" numelements="0"></hkparam>
	<hkparam name="localFrames" numelements="0"></hkparam>
</hkobject>